Metadata-Version: 2.1
Name: airbyte-cdk-velocity-amazon
Version: 0.1.1
Summary: A framework for writing Airbyte Connectors.
Home-page: https://github.com/airbytehq/airbyte
Author: Airbyte
Author-email: contact@airbyte.io
License: MIT
Project-URL: Documentation, https://docs.airbyte.io/
Project-URL: Source, https://github.com/airbytehq/airbyte
Project-URL: Tracker, https://github.com/airbytehq/airbyte/issues
Keywords: airbyte connector-development-kit cdk
Platform: UNKNOWN
Classifier: Development Status :: 3 - Alpha
Classifier: Intended Audience :: Developers
Classifier: Topic :: Scientific/Engineering
Classifier: Topic :: Software Development :: Libraries :: Python Modules
Classifier: License :: OSI Approved :: MIT License
Classifier: Programming Language :: Python :: 3.7
Classifier: Programming Language :: Python :: 3.8
Classifier: Programming Language :: Python :: 3.9
Requires-Python: >=3.7.0
License-File: LICENSE.txt
Requires-Dist: backoff
Requires-Dist: jsonschema (~=3.2.0)
Requires-Dist: pendulum
Requires-Dist: pydantic (~=1.6)
Requires-Dist: PyYAML (~=5.4)
Requires-Dist: requests
Provides-Extra: dev
Requires-Dist: MyPy (~=0.812) ; extra == 'dev'
Requires-Dist: pytest ; extra == 'dev'
Requires-Dist: pytest-cov ; extra == 'dev'
Requires-Dist: pytest-mock ; extra == 'dev'
Requires-Dist: requests-mock ; extra == 'dev'
